{"onboarding":{"$contentActions":[{"input":{"bypass":false,"$cardContent":{"document":{"id":"ce878bb6-3e27-47f8-8524-9730dc8a3066","type":"text/plain"},"editable":false,"deletable":false,"position":"right","editing":false},"$invalid":false},"$invalid":false}],"$conditionOutputs":[{"stateId":"welcome","conditions":[{"source":"input","comparison":"matches","values":[".*"]}],"$connId":"con_3","$invalid":false}],"$enteringCustomActions":[],"$leavingCustomActions":[],"$inputSuggestions":[],"$tags":[],"$defaultOutput":{"stateId":"fallback","$invalid":false},"id":"onboarding","root":true,"$position":{"top":"120px","left":"644px"},"$title":"Início","$invalidContentActions":false,"$invalidOutputs":false,"$invalidCustomActions":false,"$invalid":false},"fallback":{"$contentActions":[{"input":{"bypass":true,"$cardContent":{"document":{"id":"40c0dab2-03df-4953-a977-d17960d3fb15","type":"text/plain"},"editable":false,"deletable":true,"position":"right","editing":false},"$invalid":false},"$invalid":false}],"$conditionOutputs":[{"stateId":"error","conditions":[{"source":"input","comparison":"matches","values":[".*"]}],"$connId":"con_8","$invalid":false}],"$enteringCustomActions":[],"$leavingCustomActions":[],"$inputSuggestions":[],"$tags":[],"$defaultOutput":{"stateId":"onboarding","$invalid":false},"id":"fallback","$position":{"top":"120px","left":"877px"},"$title":"Exceções","$invalidContentActions":false,"$invalidOutputs":false,"$invalidCustomActions":false,"$invalid":false},"welcome":{"$contentActions":[{"action":{"type":"SendMessage","settings":{"id":"00000000-0000-0000-0000-000000000000","type":"application/vnd.lime.chatstate+json","content":{"state":"composing","interval":1000}},"$cardContent":{"document":{"id":"00000000-0000-0000-0000-000000000000","type":"application/vnd.lime.chatstate+json","content":{"state":"composing","interval":1000}},"editable":true,"deletable":true,"position":"left","editing":false}},"$$hashKey":"object:822","$invalid":false},{"action":{"type":"SendMessage","settings":{"id":"00000000-0000-0000-0000-000000000001","type":"text/plain","content":"Olá!! Meu nome é Sumarezinho, sou um 🤖e estou aqui para anotar todas as pérolas que ocorrem ao longo do ano de 2019 no Centro de Estudos Universitários do Sumaré."},"$cardContent":{"document":{"id":"00000000-0000-0000-0000-000000000001","type":"text/plain","content":"Olá!! Meu nome é Sumarezinho, sou um 🤖e estou aqui para anotar todas as pérolas que ocorrem ao longo do ano de 2019 no Centro de Estudos Universitários do Sumaré."},"editable":true,"deletable":true,"position":"left","editing":false}},"$$hashKey":"object:823","$invalid":false},{"action":{"type":"SendMessage","settings":{"id":"268ecba7-03c6-48ee-ae76-144b9ba0f451","type":"application/vnd.lime.chatstate+json","content":{"state":"composing","interval":1000}},"$cardContent":{"document":{"id":"268ecba7-03c6-48ee-ae76-144b9ba0f451","type":"application/vnd.lime.chatstate+json","content":{"state":"composing","interval":1000}},"editable":true,"deletable":true,"position":"left"}},"$invalid":false,"$$hashKey":"object:1164"},{"action":{"type":"SendMessage","settings":{"id":"551195d0-9629-490a-a98c-ec1b997c4fa3","type":"text/plain","content":"A edição de 2018 foi um sucesso e esperamos superar esse ano para a alegria da nação"},"$cardContent":{"document":{"id":"551195d0-9629-490a-a98c-ec1b997c4fa3","type":"text/plain","content":"A edição de 2018 foi um sucesso e esperamos superar esse ano para a alegria da nação"},"editable":true,"deletable":true,"position":"left"}},"$invalid":false,"$$hashKey":"object:1165"},{"input":{"bypass":true,"$cardContent":{"document":{"id":"918468ee-579d-4323-bb51-4e5ca484ae31","type":"text/plain","content":"Entrada do usuário"},"editable":false,"deletable":true,"position":"right","editing":false},"$invalid":false},"$$hashKey":"object:824","$invalid":false}],"$conditionOutputs":[],"$enteringCustomActions":[{"type":"TrackEvent","$title":"Registro de eventos","$invalid":false,"settings":{"extras":{},"category":"Boas Vindas","action":"Exibicao"}}],"$leavingCustomActions":[],"$inputSuggestions":[],"$tags":[],"$defaultOutput":{"stateId":"80c07abb-ceef-432e-a25b-282c8f56c2b9","$invalid":false},"id":"welcome","$position":{"top":"240px","left":"644px"},"$title":"Boas vindas","$invalidContentActions":false,"$invalidOutputs":false,"$invalidCustomActions":false,"$invalid":false},"error":{"$contentActions":[{"action":{"type":"SendMessage","settings":{"id":"00000000-0000-0000-0000-000000000002","type":"application/vnd.lime.chatstate+json","content":{"state":"composing","interval":1000}},"$cardContent":{"document":{"id":"00000000-0000-0000-0000-000000000002","type":"application/vnd.lime.chatstate+json","content":{"state":"composing","interval":1000}},"editable":true,"deletable":true,"position":"left","editing":false}},"$$hashKey":"object:7058","$invalid":false},{"action":{"type":"SendMessage","settings":{"id":"00000000-0000-0000-0000-000000000003","type":"text/plain","content":"Desculpe, não consegui entender!"},"$cardContent":{"document":{"id":"00000000-0000-0000-0000-000000000003","type":"text/plain","content":"Desculpe, não consegui entender!"},"editable":true,"deletable":true,"position":"left","editing":false}},"$$hashKey":"object:7059","$invalid":false},{"action":{"type":"SendMessage","settings":{"id":"a2737506-f69c-4706-aaf3-60a3d473b6fc","type":"application/vnd.lime.chatstate+json","content":{"state":"composing","interval":1000}},"$cardContent":{"document":{"id":"a2737506-f69c-4706-aaf3-60a3d473b6fc","type":"application/vnd.lime.chatstate+json","content":{"state":"composing","interval":1000}},"editable":true,"deletable":true,"position":"left"}},"$invalid":false,"$$hashKey":"object:7393"},{"action":{"type":"SendMessage","settings":{"id":"6b642742-fd36-40ae-8921-d1ac7b73ed4c","type":"text/plain","content":"Estou ocupado fazendo apostolado esses dias, não tive tempo ainda de treinar o meu vocabulário, mas qualquer dia podemos comer um pastel por aí 🤷‍♂️"},"$cardContent":{"document":{"id":"6b642742-fd36-40ae-8921-d1ac7b73ed4c","type":"text/plain","content":"Estou ocupado fazendo apostolado esses dias, não tive tempo ainda de treinar o meu vocabulário, mas qualquer dia podemos comer um pastel por aí 🤷‍♂️"},"editable":true,"deletable":true,"position":"left"}},"$invalid":false,"$$hashKey":"object:7394"},{"input":{"bypass":true,"$cardContent":{"document":{"id":"6233360f-9734-45e7-b592-91d5ff9f5ecd","type":"text/plain","content":"Entrada do usuário"},"editable":false,"deletable":true,"position":"right","editing":false},"$invalid":false},"$$hashKey":"object:7060","$invalid":false}],"$conditionOutputs":[],"$enteringCustomActions":[{"type":"TrackEvent","$title":"Registro de eventos","$invalid":false,"settings":{"extras":{},"category":"Exceção","action":"Exibicao"}}],"$leavingCustomActions":[],"$inputSuggestions":[],"$tags":[],"$defaultOutput":{"stateId":"welcome","$invalid":false},"id":"error","$position":{"top":"240px","left":"877px"},"$title":"Erro padrão","$invalidContentActions":false,"$invalidOutputs":false,"$invalidCustomActions":false,"$invalid":false},"a85bbc27-3036-4fd2-821e-5d657c0293e6":{"$contentActions":[{"action":{"type":"SendMessage","settings":{"id":"5521811e-0554-48c8-ba46-8070c4fbdd37","type":"application/vnd.lime.chatstate+json","content":{"state":"composing","interval":1000}},"$cardContent":{"document":{"id":"5521811e-0554-48c8-ba46-8070c4fbdd37","type":"application/vnd.lime.chatstate+json","content":{"state":"composing","interval":1000}},"editable":true,"deletable":true,"position":"left"}},"$invalid":false,"$$hashKey":"object:1937"},{"action":{"type":"SendMessage","settings":{"id":"ef08182e-e5d7-4007-a252-5107b6182b10","type":"text/plain","content":"Me conte com detalhes o ocorrido🙈. Sou discreto, manterei em segredo até encerrar o ano."},"$cardContent":{"document":{"id":"ef08182e-e5d7-4007-a252-5107b6182b10","type":"text/plain","content":"Me conte com detalhes o ocorrido🙈. Sou discreto, manterei em segredo até encerrar o ano."},"editable":true,"deletable":true,"position":"left"}},"$invalid":false,"$$hashKey":"object:1938"},{"input":{"bypass":false,"$cardContent":{"document":{"id":"548fbc51-ff53-4255-913b-125f016a18d2","type":"text/plain","textContent":"Entrada do usuário","content":"Entrada do usuário"},"editable":false,"deletable":true,"position":"right","editing":false},"$invalid":false},"$$hashKey":"object:1251","$invalid":false}],"$conditionOutputs":[],"$enteringCustomActions":[{"type":"TrackEvent","$title":"Registro de eventos","$invalid":false,"settings":{"extras":{},"category":"Detalhes da perola","action":"Exibicao"}}],"$leavingCustomActions":[{"type":"TrackEvent","$title":"Registro de eventos","$invalid":false,"settings":{"extras":{},"category":"Detalhes da perola - conteudo","action":"{{input.content}}"}}],"$inputSuggestions":[],"$tags":[],"$defaultOutput":{"stateId":"f5365ff2-c9cf-46e5-a789-e3fe928a029b","$invalid":false},"id":"a85bbc27-3036-4fd2-821e-5d657c0293e6","root":false,"$title":"Detalhes da perola","$position":{"top":"571px","left":"649px"},"$invalidContentActions":false,"$invalidOutputs":false,"$invalidCustomActions":false,"$invalid":false},"80c07abb-ceef-432e-a25b-282c8f56c2b9":{"$contentActions":[{"action":{"type":"SendMessage","settings":{"id":"42d6f84f-13c3-4740-a106-616435e8e358","type":"application/vnd.lime.chatstate+json","content":{"state":"composing","interval":1000}},"$cardContent":{"document":{"id":"42d6f84f-13c3-4740-a106-616435e8e358","type":"application/vnd.lime.chatstate+json","content":{"state":"composing","interval":1000}},"editable":true,"deletable":true,"position":"left"}},"$invalid":false,"$$hashKey":"object:2343"},{"action":{"type":"SendMessage","settings":{"id":"9e779581-eee9-4296-a44a-e0adb49d94ef","type":"text/plain","content":"Me conte primeiramente o autor da pérola ou sua sigla."},"$cardContent":{"document":{"id":"9e779581-eee9-4296-a44a-e0adb49d94ef","type":"text/plain","content":"Me conte primeiramente o autor da pérola ou sua sigla."},"editable":true,"deletable":true,"position":"left"}},"$invalid":false,"$$hashKey":"object:2344"},{"input":{"bypass":false,"$cardContent":{"document":{"id":"8c27244c-582e-4a0c-921b-9af9490c6c41","type":"text/plain","textContent":"Entrada do usuário","content":"Entrada do usuário"},"editable":false,"deletable":true,"position":"right","editing":false},"$invalid":false},"$$hashKey":"object:2021","$invalid":false}],"$conditionOutputs":[],"$enteringCustomActions":[{"type":"TrackEvent","$title":"Registro de eventos","$invalid":false,"settings":{"extras":{},"category":"Autor da Perola","action":"Exibicao"}}],"$leavingCustomActions":[{"type":"TrackEvent","$title":"Registro de eventos","$invalid":false,"settings":{"extras":{},"category":"Autor da perola - conteudo","action":"{{input.content}}"}}],"$inputSuggestions":[],"$tags":[],"$defaultOutput":{"stateId":"5e5c763b-ee38-499f-a2ea-0c95bb807a50","$invalid":false},"id":"80c07abb-ceef-432e-a25b-282c8f56c2b9","root":false,"$title":"Autor da perola","$position":{"top":"355px","left":"644px"},"$invalidContentActions":false,"$invalidOutputs":false,"$invalidCustomActions":false,"$invalid":false},"f5365ff2-c9cf-46e5-a789-e3fe928a029b":{"$contentActions":[{"action":{"type":"SendMessage","settings":{"id":"282b7a6d-5f5d-4d4a-b9d8-d06b978a8c2c","type":"application/vnd.lime.chatstate+json","content":{"state":"composing","interval":1000}},"$cardContent":{"document":{"id":"282b7a6d-5f5d-4d4a-b9d8-d06b978a8c2c","type":"application/vnd.lime.chatstate+json","content":{"state":"composing","interval":1000}},"editable":true,"deletable":true,"position":"left"}},"$invalid":false,"$$hashKey":"object:4259"},{"action":{"type":"SendMessage","settings":{"id":"f62dd4c3-7fb5-465f-9380-a48609a79196","type":"text/plain","content":"Para finalizar, me diga a data em que se passou (formato DD/MM/YYYY)"},"$cardContent":{"document":{"id":"f62dd4c3-7fb5-465f-9380-a48609a79196","type":"text/plain","content":"Para finalizar, me diga a data em que se passou (formato DD/MM/YYYY)"},"editable":true,"deletable":true,"position":"left"}},"$invalid":false,"$$hashKey":"object:4260"},{"input":{"bypass":false,"$cardContent":{"document":{"id":"faf2436e-4005-4fda-a870-39852651fa87","type":"text/plain","textContent":"Entrada do usuário","content":"Entrada do usuário"},"editable":false,"deletable":true,"position":"right","editing":false},"$invalid":false},"$$hashKey":"object:3191","$invalid":false}],"$conditionOutputs":[{"stateId":"13b40127-5873-46ac-99fb-9095b60538ab","$connId":"con_13","conditions":[{"source":"input","comparison":"matches","values":["^(0[1-9]|[12][0-9]|3[01])\\/(0[1-9]|1[012])\\/[12][0-9]{3}$"],"$$hashKey":"object:12823","entity":"^(0[1-9]|[12][0-9]|3[01])\\/(0[1-9]|1[012])\\/[12][0-9]{3}$"}],"$invalid":false,"$$hashKey":"object:12814"}],"$enteringCustomActions":[{"type":"TrackEvent","$title":"Registro de eventos","$invalid":false,"settings":{"extras":{},"category":"Data da perola","action":"Exibicao"}}],"$leavingCustomActions":[{"type":"TrackEvent","$title":"Registro de eventos","$invalid":false,"settings":{"extras":{},"category":"Data da perola - data","action":"{{input.content}}"}}],"$inputSuggestions":[],"$tags":[],"$defaultOutput":{"stateId":"1fd6a00a-e550-4af5-8222-51fa2eaa5357","$invalid":false},"id":"f5365ff2-c9cf-46e5-a789-e3fe928a029b","root":false,"$title":"Data da perola","$position":{"top":"673px","left":"644px"},"$invalidContentActions":false,"$invalidOutputs":false,"$invalidCustomActions":false,"$invalid":false},"13b40127-5873-46ac-99fb-9095b60538ab":{"$contentActions":[{"action":{"type":"SendMessage","settings":{"id":"c436c2fd-5f0e-4271-be45-bc7d240a9130","type":"application/vnd.lime.chatstate+json","content":{"state":"composing","interval":1000}},"$cardContent":{"document":{"id":"c436c2fd-5f0e-4271-be45-bc7d240a9130","type":"application/vnd.lime.chatstate+json","content":{"state":"composing","interval":1000}},"editable":true,"deletable":true,"position":"left"}},"$invalid":false,"$$hashKey":"object:4665"},{"action":{"type":"SendMessage","settings":{"id":"c28e7bcb-a71f-4aff-81e0-68205fe08bff","type":"text/plain","content":"Muito obrigado! Você contribuiu bastante para melhorar o ambiente e o saldo de cada autor de pérolas."},"$cardContent":{"document":{"id":"c28e7bcb-a71f-4aff-81e0-68205fe08bff","type":"text/plain","content":"Muito obrigado! Você contribuiu bastante para melhorar o ambiente e o saldo de cada autor de pérolas."},"editable":true,"deletable":true,"position":"left"}},"$invalid":false,"$$hashKey":"object:4666"},{"action":{"type":"SendMessage","settings":{"id":"f960a4ac-0d52-4687-8449-2ea378ccc6b6","type":"application/vnd.lime.chatstate+json","content":{"state":"composing","interval":1000}},"$cardContent":{"document":{"id":"f960a4ac-0d52-4687-8449-2ea378ccc6b6","type":"application/vnd.lime.chatstate+json","content":{"state":"composing","interval":1000}},"editable":true,"deletable":true,"position":"left"}},"$invalid":false,"$$hashKey":"object:4685"},{"action":{"type":"SendMessage","settings":{"id":"7453f353-8238-43f6-ac0b-70e183255be8","type":"text/plain","content":"Sempre que acontecer alguma pérola não deixe de me avisar 😉"},"$cardContent":{"document":{"id":"7453f353-8238-43f6-ac0b-70e183255be8","type":"text/plain","content":"Sempre que acontecer alguma pérola não deixe de me avisar 😉"},"editable":true,"deletable":true,"position":"left"}},"$invalid":false,"$$hashKey":"object:4686"},{"input":{"bypass":false,"$cardContent":{"document":{"id":"f091166a-7f63-455b-82d7-bce461e9689e","type":"text/plain","textContent":"Entrada do usuário","content":"Entrada do usuário"},"editable":false,"deletable":true,"position":"right","editing":false},"$invalid":false},"$$hashKey":"object:4343","$invalid":false}],"$conditionOutputs":[],"$enteringCustomActions":[{"type":"TrackEvent","$title":"Registro de eventos","$invalid":false,"settings":{"extras":{},"category":"Finalizado","action":"Exibicao"}}],"$leavingCustomActions":[{"type":"TrackEvent","$title":"Registro de eventos","$invalid":false,"settings":{"extras":{},"category":"Finalizado - conteudo","action":"{{input.content}}"}}],"$inputSuggestions":[],"$tags":[],"$defaultOutput":{"stateId":"fallback","$invalid":false},"id":"13b40127-5873-46ac-99fb-9095b60538ab","root":false,"$title":"Finalizado","$position":{"top":"775px","left":"646px"},"$invalidContentActions":false,"$invalidOutputs":false,"$invalidCustomActions":false,"$invalid":false},"1fd6a00a-e550-4af5-8222-51fa2eaa5357":{"$contentActions":[{"action":{"type":"SendMessage","settings":{"id":"40a48132-fe64-4ce5-a859-034c6fbe7a03","type":"application/vnd.lime.chatstate+json","content":{"state":"composing","interval":1000}},"$cardContent":{"document":{"id":"40a48132-fe64-4ce5-a859-034c6fbe7a03","type":"application/vnd.lime.chatstate+json","content":{"state":"composing","interval":1000}},"editable":true,"deletable":true,"position":"left"}},"$invalid":false,"$$hashKey":"object:13253"},{"action":{"type":"SendMessage","settings":{"id":"79aec8ae-f7b1-44cf-9f65-c962edf218ee","type":"text/plain","content":"Pow meu, vc forneceu uma data errada! Tente novamente."},"$cardContent":{"document":{"id":"79aec8ae-f7b1-44cf-9f65-c962edf218ee","type":"text/plain","content":"Pow meu, vc forneceu uma data errada! Tente novamente."},"editable":true,"deletable":true,"position":"left"}},"$invalid":false,"$$hashKey":"object:13254"},{"input":{"bypass":false,"$cardContent":{"document":{"id":"01f9def7-327c-4d5a-875e-aa7b76830b32","type":"text/plain","textContent":"Entrada do usuário","content":"Entrada do usuário"},"editable":false,"deletable":true,"position":"right","editing":false},"$invalid":false},"$$hashKey":"object:12931","$invalid":false}],"$conditionOutputs":[{"stateId":"13b40127-5873-46ac-99fb-9095b60538ab","$connId":"con_18","conditions":[{"source":"input","comparison":"matches","values":["^(0[1-9]|[12][0-9]|3[01])\\/(0[1-9]|1[012])\\/[12][0-9]{3}$"],"$$hashKey":"object:13282"}],"$invalid":false,"$$hashKey":"object:13273"}],"$enteringCustomActions":[{"type":"TrackEvent","$title":"Registro de eventos","$invalid":false,"settings":{"extras":{},"category":"Data da perola - segunda tentativa","action":"Exibicao"}}],"$leavingCustomActions":[{"type":"TrackEvent","$title":"Registro de eventos","$invalid":false,"settings":{"extras":{},"category":"Data da perola - segunda tentativa - conteudo","action":"{{input.content}}"}}],"$inputSuggestions":[],"$tags":[],"$defaultOutput":{"stateId":"1fd6a00a-e550-4af5-8222-51fa2eaa5357","$invalid":false},"id":"1fd6a00a-e550-4af5-8222-51fa2eaa5357","root":false,"$title":"Data da perola - segunda tentativa","$position":{"top":"566px","left":"862px"},"$invalidContentActions":false,"$invalidOutputs":false,"$invalidCustomActions":false,"$invalid":false},"5e5c763b-ee38-499f-a2ea-0c95bb807a50":{"$contentActions":[{"action":{"type":"SendMessage","settings":{"id":"fb4e5f8f-947a-41e1-bf49-d79e2a54815f","type":"application/vnd.lime.chatstate+json","content":{"state":"composing","interval":1000}},"$cardContent":{"document":{"id":"fb4e5f8f-947a-41e1-bf49-d79e2a54815f","type":"application/vnd.lime.chatstate+json","content":{"state":"composing","interval":1000}},"editable":true,"deletable":true,"position":"left"}},"$invalid":false,"$$hashKey":"object:15327"},{"action":{"type":"SendMessage","settings":{"id":"31aa910b-f0a0-49eb-aee2-00476e71b232","type":"text/plain","content":"Ah tinha que ser ele! Esse cara é campeão de pérolas 😂😂😂"},"$cardContent":{"document":{"id":"31aa910b-f0a0-49eb-aee2-00476e71b232","type":"text/plain","content":"Ah tinha que ser ele! Esse cara é campeão de pérolas 😂😂😂"},"editable":true,"deletable":true,"position":"left"}},"$invalid":false,"$$hashKey":"object:15328"},{"input":{"bypass":true,"$cardContent":{"document":{"id":"55aa5754-6259-4136-9ff3-ccd5dd64b094","type":"text/plain","content":"Entrada do usuário"},"editable":false,"deletable":true,"position":"right","editing":false},"$invalid":false},"$$hashKey":"object:14641","$invalid":false}],"$conditionOutputs":[],"$enteringCustomActions":[{"type":"TrackEvent","$title":"Registro de eventos","$invalid":false,"settings":{"extras":{},"category":"Tinha que ser ele","action":"Exibicao"}}],"$leavingCustomActions":[],"$inputSuggestions":[],"$tags":[],"$defaultOutput":{"stateId":"a85bbc27-3036-4fd2-821e-5d657c0293e6","$invalid":false},"id":"5e5c763b-ee38-499f-a2ea-0c95bb807a50","root":false,"$title":"Tinha que ser ele","$position":{"top":"463px","left":"649px"},"$invalidContentActions":false,"$invalidOutputs":false,"$invalidCustomActions":false,"$invalid":false}}